webwidgets/__init__.py
webwidgets/compilation/__init__.py
webwidgets/compilation/css/__init__.py
webwidgets/compilation/css/css.py
webwidgets/compilation/css/css_rule.py
webwidgets/compilation/css/sections/__init__.py
webwidgets/compilation/css/sections/css_section.py
webwidgets/compilation/css/sections/preamble.py
webwidgets/compilation/css/sections/rule_section.py
webwidgets/compilation/html/__init__.py
webwidgets/compilation/html/html_node.py
webwidgets/compilation/html/html_tags.py
webwidgets/utility/__init__.py
webwidgets/utility/enums.py
webwidgets/utility/indentation.py
webwidgets/utility/representation.py
webwidgets/utility/sanitizing.py
webwidgets/utility/validation.py
webwidgets/utility/sizes/__init__.py
webwidgets/utility/sizes/size.py
webwidgets/utility/sizes/sizes.py
webwidgets/website/__init__.py
webwidgets/website/compiled_website.py
webwidgets/website/website.py
webwidgets/widgets/__init__.py
webwidgets/widgets/widget.py
webwidgets/widgets/containers/__init__.py
webwidgets/widgets/containers/box.py
webwidgets/widgets/containers/container.py
webwidgets/widgets/containers/page.py
webwidgets-1.1.1.dist-info/METADATA
webwidgets-1.1.1.dist-info/WHEEL
webwidgets-1.1.1.dist-info/licenses/LICENSE
webwidgets-1.1.1.dist-info/RECORD
