Metadata-Version: 2.4
Name: webwidgets
Version: 1.1.1
Summary: A Python package for designing web UIs.
Project-URL: Source code, https://github.com/mlaasri/WebWidgets
Author: mlaasri
License-File: LICENSE
Keywords: design,webui
Classifier: Operating System :: OS Independent
Classifier: Programming Language :: Python :: 3
Requires-Python: >=3.9
Provides-Extra: dev
Requires-Dist: numpy; extra == 'dev'
Requires-Dist: pillow; extra == 'dev'
Requires-Dist: pytest; extra == 'dev'
Requires-Dist: selenium; extra == 'dev'
